{"entries":[{"playerName":"TheJazs2","playerDisplayName":"TheJazs2","prefix":"\u0026fꔡ\u00267","suffix":"\u00266\u0026l+","playerID":"6c03c403-b611-38cc-921c-3ab8080f5104","position":1,"board":"statistic_player_kills","type":"WEEKLY","score":225.0},{"playerName":"1mort0","playerDisplayName":"1mort0","prefix":"\u0026fꔡ\u00267","suffix":"\u0026x\u00260\u00260\u00267\u0026b\u0026f\u0026b\u0026l","playerID":"83d8dee4-8dd2-31f1-8be5-3faf89f01df7","position":2,"board":"statistic_player_kills","type":"WEEKLY","score":150.0},{"playerName":"_JIFVEL992_","playerDisplayName":"_JIFVEL992_","prefix":"\u0026fꔨ\u00267","suffix":"","playerID":"573c9b69-9c94-39eb-bcce-bccc6e835a78","position":3,"board":"statistic_player_kills","type":"WEEKLY","score":147.0},{"playerName":"hoklivenroon","playerDisplayName":"hoklivenroon","prefix":"\u0026fꔨ\u00267","suffix":"\u00266\u0026l+","playerID":"8d732514-da5c-3dd1-8b15-31b97a2d23ac","position":4,"board":"statistic_player_kills","type":"WEEKLY","score":144.0},{"playerName":"neles54","playerDisplayName":"neles54","prefix":"\u0026fꔨ\u00267","suffix":"\u00266\u0026l+","playerID":"8d46cb1f-fe35-316e-9be3-3888c55f1e91","position":5,"board":"statistic_player_kills","type":"WEEKLY","score":127.0},{"playerName":"zXXEMgeVt","playerDisplayName":"zXXEMgeVt","prefix":"\u0026fꔨ\u00267","suffix":"\u00266\u0026l+","playerID":"f0904ddc-d2b4-3125-ad21-7cbb70d7e1fe","position":6,"board":"statistic_player_kills","type":"WEEKLY","score":119.0},{"playerName":"ItzKirill_","playerDisplayName":"ItzKirill_","prefix":"\u0026fꔀ\u00267","suffix":"","playerID":"653ae30f-76f9-3372-957e-0d9d8fdd4318","position":7,"board":"statistic_player_kills","type":"WEEKLY","score":113.0},{"playerName":"ne_grox_twink_2","playerDisplayName":"ne_grox_twink_2","prefix":"\u0026fꕁ\u00267","suffix":"","playerID":"4b91af7e-3128-357e-a601-ef02e229dc5d","position":8,"board":"statistic_player_kills","type":"WEEKLY","score":108.0},{"playerName":"ShinaLoi","playerDisplayName":"ShinaLoi","prefix":"\u0026fꔨ\u00267","suffix":"","playerID":"e82d96a9-069d-308b-a400-e9f1d9d2df13","position":9,"board":"statistic_player_kills","type":"WEEKLY","score":107.0},{"playerName":"GIF9Qki","playerDisplayName":"GIF9Qki","prefix":"\u0026fꕅ\u00267","suffix":"\u00266\u0026l+","playerID":"62a32904-4d04-3731-b99a-ebf9ab6977af","position":10,"board":"statistic_player_kills","type":"WEEKLY","score":104.0}],"meta":{"time":1768089600260,"type":"WEEKLY","board":"statistic_player_kills"}}